authed_mcp/client.py
authed_mcp/server.py
authed_mcp-0.2.0.dist-info/METADATA
authed_mcp-0.2.0.dist-info/WHEEL
authed_mcp-0.2.0.dist-info/entry_points.txt
authed_mcp-0.2.0.dist-info/top_level.txt
authed_mcp-0.2.0.dist-info/RECORD
