Metadata-Version: 2.4
Name: authed-mcp
Version: 0.2.0
Summary: Authed authentication integration for Model Context Protocol (MCP)
Author-email: Antoni Gmitruk <antoni@getauthed.dev>
License: MIT
Project-URL: Documentation, https://docs.getauthed.dev
Project-URL: Source code, https://github.com/authed-dev/authed/tree/master/integrations/authed_mcp
Project-URL: Homepage, https://getauthed.dev
Project-URL: Bug Tracker, https://github.com/authed-dev/authed/issues
Classifier: Development Status :: 3 - Alpha
Classifier: Intended Audience :: Developers
Classifier: License :: OSI Approved :: MIT License
Classifier: Programming Language :: Python :: 3
Classifier: Programming Language :: Python :: 3.8
Classifier: Programming Language :: Python :: 3.9
Classifier: Programming Language :: Python :: 3.10
Classifier: Programming Language :: Python :: 3.11
Requires-Python: >=3.8
Requires-Dist: authed>=0.2.0
Requires-Dist: mcp>=1.4.0
Requires-Dist: httpx>=0.28.0
Requires-Dist: uvicorn>=0.34.0
Requires-Dist: starlette>=0.46.1
Requires-Dist: pyjwt>=2.10.1
Requires-Dist: cryptography>=44.0.2
Requires-Dist: python-dotenv>=1.0.0
